{
  "name": "sofl",
  "word": "identifier",
  "rules": {
    "source_file": {
      "type": "SEQ",
      "members": [
        {
          "type": "SYMBOL",
          "name": "module_definition"
        },
        {
          "type": "CHOICE",
          "members": [
            {
              "type": "SYMBOL",
              "name": "type_definition"
            },
            {
              "type": "BLANK"
            }
          ]
        },
        {
          "type": "CHOICE",
          "members": [
            {
              "type": "SYMBOL",
              "name": "variable_definition"
            },
            {
              "type": "BLANK"
            }
          ]
        },
        {
          "type": "CHOICE",
          "members": [
            {
              "type": "SYMBOL",
              "name": "process_definition"
            },
            {
              "type": "BLANK"
            }
          ]
        }
      ]
    },
    "module_definition": {
      "type": "SEQ",
      "members": [
        {
          "type": "STRING",
          "value": "module"
        },
        {
          "type": "FIELD",
          "name": "module_name",
          "content": {
            "type": "SYMBOL",
            "name": "identifier"
          }
        },
        {
          "type": "CHOICE",
          "members": [
            {
              "type": "SEQ",
              "members": [
                {
                  "type": "STRING",
                  "value": "/"
                },
                {
                  "type": "SYMBOL",
                  "name": "identifier"
                }
              ]
            },
            {
              "type": "BLANK"
            }
          ]
        },
        {
          "type": "SYMBOL",
          "name": "_semicolon"
        }
      ]
    },
    "type_definition": {
      "type": "SEQ",
      "members": [
        {
          "type": "STRING",
          "value": "type"
        },
        {
          "type": "REPEAT1",
          "content": {
            "type": "SYMBOL",
            "name": "type_definition_item"
          }
        }
      ]
    },
    "type_definition_item": {
      "type": "SEQ",
      "members": [
        {
          "type": "SYMBOL",
          "name": "identifier"
        },
        {
          "type": "STRING",
          "value": "="
        },
        {
          "type": "SYMBOL",
          "name": "_type"
        },
        {
          "type": "SYMBOL",
          "name": "_semicolon"
        }
      ]
    },
    "variable_definition": {
      "type": "SEQ",
      "members": [
        {
          "type": "STRING",
          "value": "var"
        },
        {
          "type": "REPEAT1",
          "content": {
            "type": "SYMBOL",
            "name": "variable_definition_item"
          }
        }
      ]
    },
    "variable_definition_item": {
      "type": "SEQ",
      "members": [
        {
          "type": "SYMBOL",
          "name": "identifier"
        },
        {
          "type": "STRING",
          "value": ":"
        },
        {
          "type": "SYMBOL",
          "name": "_type"
        },
        {
          "type": "SYMBOL",
          "name": "_semicolon"
        }
      ]
    },
    "process_definition": {
      "type": "REPEAT1",
      "content": {
        "type": "SYMBOL",
        "name": "process_definition_item"
      }
    },
    "process_definition_item": {
      "type": "SEQ",
      "members": [
        {
          "type": "STRING",
          "value": "process"
        },
        {
          "type": "SYMBOL",
          "name": "identifier"
        },
        {
          "type": "STRING",
          "value": "("
        },
        {
          "type": "CHOICE",
          "members": [
            {
              "type": "SYMBOL",
              "name": "parameter_list"
            },
            {
              "type": "BLANK"
            }
          ]
        },
        {
          "type": "STRING",
          "value": ")"
        },
        {
          "type": "CHOICE",
          "members": [
            {
              "type": "SYMBOL",
              "name": "parameter_list"
            },
            {
              "type": "BLANK"
            }
          ]
        },
        {
          "type": "SYMBOL",
          "name": "process_body"
        },
        {
          "type": "STRING",
          "value": "end_process"
        },
        {
          "type": "SYMBOL",
          "name": "_semicolon"
        }
      ]
    },
    "parameter_list": {
      "type": "SEQ",
      "members": [
        {
          "type": "SYMBOL",
          "name": "parameter_item"
        },
        {
          "type": "REPEAT",
          "content": {
            "type": "SEQ",
            "members": [
              {
                "type": "STRING",
                "value": "|"
              },
              {
                "type": "SYMBOL",
                "name": "parameter_item"
              }
            ]
          }
        }
      ]
    },
    "parameter_item": {
      "type": "SEQ",
      "members": [
        {
          "type": "SYMBOL",
          "name": "identifier"
        },
        {
          "type": "REPEAT",
          "content": {
            "type": "SEQ",
            "members": [
              {
                "type": "STRING",
                "value": ","
              },
              {
                "type": "SYMBOL",
                "name": "identifier"
              }
            ]
          }
        },
        {
          "type": "STRING",
          "value": ":"
        },
        {
          "type": "CHOICE",
          "members": [
            {
              "type": "SYMBOL",
              "name": "_type"
            },
            {
              "type": "SYMBOL",
              "name": "_expression"
            }
          ]
        }
      ]
    },
    "process_body": {
      "type": "SEQ",
      "members": [
        {
          "type": "CHOICE",
          "members": [
            {
              "type": "SEQ",
              "members": [
                {
                  "type": "STRING",
                  "value": "ext"
                },
                {
                  "type": "REPEAT1",
                  "content": {
                    "type": "SYMBOL",
                    "name": "ext_item"
                  }
                }
              ]
            },
            {
              "type": "BLANK"
            }
          ]
        },
        {
          "type": "SEQ",
          "members": [
            {
              "type": "STRING",
              "value": "pre"
            },
            {
              "type": "SYMBOL",
              "name": "_expression"
            }
          ]
        },
        {
          "type": "SEQ",
          "members": [
            {
              "type": "STRING",
              "value": "post"
            },
            {
              "type": "SYMBOL",
              "name": "_expression"
            }
          ]
        }
      ]
    },
    "ext_item": {
      "type": "SEQ",
      "members": [
        {
          "type": "CHOICE",
          "members": [
            {
              "type": "STRING",
              "value": "wr"
            },
            {
              "type": "STRING",
              "value": "rd"
            }
          ]
        },
        {
          "type": "SYMBOL",
          "name": "identifier"
        },
        {
          "type": "STRING",
          "value": ":"
        },
        {
          "type": "SYMBOL",
          "name": "_type"
        }
      ]
    },
    "_type": {
      "type": "PREC_LEFT",
      "value": 1,
      "content": {
        "type": "CHOICE",
        "members": [
          {
            "type": "SYMBOL",
            "name": "type_identifier"
          },
          {
            "type": "SYMBOL",
            "name": "primitive_type"
          },
          {
            "type": "SYMBOL",
            "name": "enumeration_type"
          },
          {
            "type": "SYMBOL",
            "name": "set_type"
          },
          {
            "type": "SYMBOL",
            "name": "list_type"
          },
          {
            "type": "SYMBOL",
            "name": "map_type"
          },
          {
            "type": "SYMBOL",
            "name": "composite_type"
          }
        ]
      }
    },
    "type_identifier": {
      "type": "PREC",
      "value": 1,
      "content": {
        "type": "SYMBOL",
        "name": "identifier"
      }
    },
    "primitive_type": {
      "type": "CHOICE",
      "members": [
        {
          "type": "STRING",
          "value": "nat"
        },
        {
          "type": "STRING",
          "value": "nat0"
        },
        {
          "type": "STRING",
          "value": "real"
        },
        {
          "type": "STRING",
          "value": "int"
        },
        {
          "type": "STRING",
          "value": "bool"
        },
        {
          "type": "STRING",
          "value": "char"
        },
        {
          "type": "STRING",
          "value": "string"
        }
      ]
    },
    "enumeration_type": {
      "type": "SEQ",
      "members": [
        {
          "type": "STRING",
          "value": "{"
        },
        {
          "type": "SEQ",
          "members": [
            {
              "type": "SYMBOL",
              "name": "enumeration_value"
            },
            {
              "type": "REPEAT",
              "content": {
                "type": "SEQ",
                "members": [
                  {
                    "type": "STRING",
                    "value": ","
                  },
                  {
                    "type": "SYMBOL",
                    "name": "enumeration_value"
                  }
                ]
              }
            }
          ]
        },
        {
          "type": "STRING",
          "value": "}"
        }
      ]
    },
    "enumeration_value": {
      "type": "SEQ",
      "members": [
        {
          "type": "STRING",
          "value": "<"
        },
        {
          "type": "SYMBOL",
          "name": "identifier"
        },
        {
          "type": "STRING",
          "value": ">"
        }
      ]
    },
    "set_type": {
      "type": "SEQ",
      "members": [
        {
          "type": "STRING",
          "value": "set"
        },
        {
          "type": "STRING",
          "value": "of"
        },
        {
          "type": "SYMBOL",
          "name": "_type"
        }
      ]
    },
    "list_type": {
      "type": "SEQ",
      "members": [
        {
          "type": "STRING",
          "value": "list"
        },
        {
          "type": "STRING",
          "value": "of"
        },
        {
          "type": "SYMBOL",
          "name": "_type"
        }
      ]
    },
    "map_type": {
      "type": "SEQ",
      "members": [
        {
          "type": "STRING",
          "value": "map"
        },
        {
          "type": "FIELD",
          "name": "key",
          "content": {
            "type": "SYMBOL",
            "name": "_type"
          }
        },
        {
          "type": "STRING",
          "value": "to"
        },
        {
          "type": "FIELD",
          "name": "value",
          "content": {
            "type": "SYMBOL",
            "name": "_type"
          }
        }
      ]
    },
    "composite_type": {
      "type": "SEQ",
      "members": [
        {
          "type": "STRING",
          "value": "composed"
        },
        {
          "type": "STRING",
          "value": "of"
        },
        {
          "type": "REPEAT",
          "content": {
            "type": "FIELD",
            "name": "field",
            "content": {
              "type": "SEQ",
              "members": [
                {
                  "type": "FIELD",
                  "name": "filed_name",
                  "content": {
                    "type": "SYMBOL",
                    "name": "identifier"
                  }
                },
                {
                  "type": "STRING",
                  "value": ":"
                },
                {
                  "type": "FIELD",
                  "name": "field_type",
                  "content": {
                    "type": "SYMBOL",
                    "name": "_type"
                  }
                },
                {
                  "type": "SYMBOL",
                  "name": "_semicolon"
                }
              ]
            }
          }
        },
        {
          "type": "STRING",
          "value": "end"
        }
      ]
    },
    "_expression": {
      "type": "CHOICE",
      "members": [
        {
          "type": "SYMBOL",
          "name": "_constant_expression"
        },
        {
          "type": "SYMBOL",
          "name": "unary_expression"
        },
        {
          "type": "SYMBOL",
          "name": "binary_expression"
        },
        {
          "type": "SYMBOL",
          "name": "reference_expression"
        },
        {
          "type": "SYMBOL",
          "name": "modify_expression"
        },
        {
          "type": "SYMBOL",
          "name": "function_expression"
        },
        {
          "type": "SYMBOL",
          "name": "quantified_expression"
        },
        {
          "type": "SEQ",
          "members": [
            {
              "type": "STRING",
              "value": "("
            },
            {
              "type": "SYMBOL",
              "name": "_expression"
            },
            {
              "type": "STRING",
              "value": ")"
            }
          ]
        }
      ]
    },
    "expression_list": {
      "type": "SEQ",
      "members": [
        {
          "type": "SYMBOL",
          "name": "_expression"
        },
        {
          "type": "REPEAT",
          "content": {
            "type": "SEQ",
            "members": [
              {
                "type": "STRING",
                "value": ","
              },
              {
                "type": "SYMBOL",
                "name": "_expression"
              }
            ]
          }
        }
      ]
    },
    "_constant_expression": {
      "type": "CHOICE",
      "members": [
        {
          "type": "SYMBOL",
          "name": "int"
        },
        {
          "type": "SYMBOL",
          "name": "real"
        },
        {
          "type": "SYMBOL",
          "name": "string"
        },
        {
          "type": "SYMBOL",
          "name": "char"
        },
        {
          "type": "SYMBOL",
          "name": "bool"
        },
        {
          "type": "SYMBOL",
          "name": "list_expression"
        },
        {
          "type": "SYMBOL",
          "name": "map_expression"
        }
      ]
    },
    "reference_expression": {
      "type": "CHOICE",
      "members": [
        {
          "type": "SYMBOL",
          "name": "identifier"
        },
        {
          "type": "SEQ",
          "members": [
            {
              "type": "SYMBOL",
              "name": "reference_expression"
            },
            {
              "type": "STRING",
              "value": "."
            },
            {
              "type": "SYMBOL",
              "name": "identifier"
            }
          ]
        }
      ]
    },
    "list_expression": {
      "type": "SEQ",
      "members": [
        {
          "type": "STRING",
          "value": "{"
        },
        {
          "type": "CHOICE",
          "members": [
            {
              "type": "FIELD",
              "name": "items",
              "content": {
                "type": "SYMBOL",
                "name": "expression_list"
              }
            },
            {
              "type": "BLANK"
            }
          ]
        },
        {
          "type": "STRING",
          "value": "}"
        }
      ]
    },
    "map_expression": {
      "type": "SEQ",
      "members": [
        {
          "type": "STRING",
          "value": "{"
        },
        {
          "type": "CHOICE",
          "members": [
            {
              "type": "STRING",
              "value": "->"
            },
            {
              "type": "SEQ",
              "members": [
                {
                  "type": "SYMBOL",
                  "name": "map_item"
                },
                {
                  "type": "REPEAT",
                  "content": {
                    "type": "SEQ",
                    "members": [
                      {
                        "type": "STRING",
                        "value": ","
                      },
                      {
                        "type": "SYMBOL",
                        "name": "map_item"
                      }
                    ]
                  }
                }
              ]
            }
          ]
        },
        {
          "type": "STRING",
          "value": "}"
        }
      ]
    },
    "map_item": {
      "type": "SEQ",
      "members": [
        {
          "type": "FIELD",
          "name": "key",
          "content": {
            "type": "SYMBOL",
            "name": "_expression"
          }
        },
        {
          "type": "STRING",
          "value": "->"
        },
        {
          "type": "FIELD",
          "name": "value",
          "content": {
            "type": "SYMBOL",
            "name": "_expression"
          }
        }
      ]
    },
    "unary_expression": {
      "type": "PREC",
      "value": 11,
      "content": {
        "type": "SEQ",
        "members": [
          {
            "type": "CHOICE",
            "members": [
              {
                "type": "STRING",
                "value": "-"
              },
              {
                "type": "STRING",
                "value": "not"
              },
              {
                "type": "STRING",
                "value": "~"
              }
            ]
          },
          {
            "type": "SYMBOL",
            "name": "_expression"
          }
        ]
      }
    },
    "binary_expression": {
      "type": "CHOICE",
      "members": [
        {
          "type": "PREC_LEFT",
          "value": 10,
          "content": {
            "type": "SEQ",
            "members": [
              {
                "type": "SYMBOL",
                "name": "_expression"
              },
              {
                "type": "CHOICE",
                "members": [
                  {
                    "type": "STRING",
                    "value": "="
                  },
                  {
                    "type": "STRING",
                    "value": "<>"
                  },
                  {
                    "type": "STRING",
                    "value": "<"
                  },
                  {
                    "type": "STRING",
                    "value": "<="
                  },
                  {
                    "type": "STRING",
                    "value": ">"
                  },
                  {
                    "type": "STRING",
                    "value": ">="
                  },
                  {
                    "type": "STRING",
                    "value": "inset"
                  },
                  {
                    "type": "STRING",
                    "value": "notinset"
                  }
                ]
              },
              {
                "type": "SYMBOL",
                "name": "_expression"
              }
            ]
          }
        },
        {
          "type": "PREC_LEFT",
          "value": 9,
          "content": {
            "type": "SEQ",
            "members": [
              {
                "type": "SYMBOL",
                "name": "_expression"
              },
              {
                "type": "CHOICE",
                "members": [
                  {
                    "type": "STRING",
                    "value": "*"
                  },
                  {
                    "type": "STRING",
                    "value": "/"
                  },
                  {
                    "type": "STRING",
                    "value": "div"
                  },
                  {
                    "type": "STRING",
                    "value": "rem"
                  },
                  {
                    "type": "STRING",
                    "value": "mod"
                  }
                ]
              },
              {
                "type": "SYMBOL",
                "name": "_expression"
              }
            ]
          }
        },
        {
          "type": "PREC_LEFT",
          "value": 8,
          "content": {
            "type": "SEQ",
            "members": [
              {
                "type": "SYMBOL",
                "name": "_expression"
              },
              {
                "type": "CHOICE",
                "members": [
                  {
                    "type": "STRING",
                    "value": "+"
                  },
                  {
                    "type": "STRING",
                    "value": "-"
                  }
                ]
              },
              {
                "type": "SYMBOL",
                "name": "_expression"
              }
            ]
          }
        },
        {
          "type": "PREC_LEFT",
          "value": 7,
          "content": {
            "type": "SEQ",
            "members": [
              {
                "type": "SYMBOL",
                "name": "_expression"
              },
              {
                "type": "CHOICE",
                "members": [
                  {
                    "type": "STRING",
                    "value": "and"
                  }
                ]
              },
              {
                "type": "SYMBOL",
                "name": "_expression"
              }
            ]
          }
        },
        {
          "type": "PREC_LEFT",
          "value": 6,
          "content": {
            "type": "SEQ",
            "members": [
              {
                "type": "SYMBOL",
                "name": "_expression"
              },
              {
                "type": "CHOICE",
                "members": [
                  {
                    "type": "STRING",
                    "value": "or"
                  }
                ]
              },
              {
                "type": "SYMBOL",
                "name": "_expression"
              }
            ]
          }
        },
        {
          "type": "PREC_LEFT",
          "value": 5,
          "content": {
            "type": "SEQ",
            "members": [
              {
                "type": "SYMBOL",
                "name": "_expression"
              },
              {
                "type": "CHOICE",
                "members": [
                  {
                    "type": "STRING",
                    "value": "=>"
                  },
                  {
                    "type": "STRING",
                    "value": "<=>"
                  }
                ]
              },
              {
                "type": "SYMBOL",
                "name": "_expression"
              }
            ]
          }
        }
      ]
    },
    "modify_expression": {
      "type": "SEQ",
      "members": [
        {
          "type": "STRING",
          "value": "modify"
        },
        {
          "type": "STRING",
          "value": "("
        },
        {
          "type": "SYMBOL",
          "name": "reference_expression"
        },
        {
          "type": "STRING",
          "value": ","
        },
        {
          "type": "SEQ",
          "members": [
            {
              "type": "SEQ",
              "members": [
                {
                  "type": "SYMBOL",
                  "name": "identifier"
                },
                {
                  "type": "STRING",
                  "value": "->"
                },
                {
                  "type": "SYMBOL",
                  "name": "_expression"
                }
              ]
            },
            {
              "type": "REPEAT",
              "content": {
                "type": "SEQ",
                "members": [
                  {
                    "type": "STRING",
                    "value": ","
                  },
                  {
                    "type": "SEQ",
                    "members": [
                      {
                        "type": "SYMBOL",
                        "name": "identifier"
                      },
                      {
                        "type": "STRING",
                        "value": "->"
                      },
                      {
                        "type": "SYMBOL",
                        "name": "_expression"
                      }
                    ]
                  }
                ]
              }
            }
          ]
        },
        {
          "type": "STRING",
          "value": ")"
        }
      ]
    },
    "function_expression": {
      "type": "SEQ",
      "members": [
        {
          "type": "SYMBOL",
          "name": "identifier"
        },
        {
          "type": "STRING",
          "value": "("
        },
        {
          "type": "CHOICE",
          "members": [
            {
              "type": "SYMBOL",
              "name": "expression_list"
            },
            {
              "type": "BLANK"
            }
          ]
        },
        {
          "type": "STRING",
          "value": ")"
        }
      ]
    },
    "quantified_expression": {
      "type": "SEQ",
      "members": [
        {
          "type": "CHOICE",
          "members": [
            {
              "type": "STRING",
              "value": "forall"
            },
            {
              "type": "STRING",
              "value": "exists"
            }
          ]
        },
        {
          "type": "STRING",
          "value": "["
        },
        {
          "type": "SYMBOL",
          "name": "binding_list"
        },
        {
          "type": "STRING",
          "value": "]"
        },
        {
          "type": "SYMBOL",
          "name": "_expression"
        }
      ]
    },
    "binding_list": {
      "type": "SEQ",
      "members": [
        {
          "type": "SYMBOL",
          "name": "parameter_item"
        },
        {
          "type": "REPEAT",
          "content": {
            "type": "SEQ",
            "members": [
              {
                "type": "STRING",
                "value": ","
              },
              {
                "type": "SYMBOL",
                "name": "parameter_item"
              }
            ]
          }
        }
      ]
    },
    "int": {
      "type": "PATTERN",
      "value": "-?\\d+"
    },
    "real": {
      "type": "PATTERN",
      "value": "-?\\d+\\.\\d+"
    },
    "string": {
      "type": "PATTERN",
      "value": "\"[^\"]*\""
    },
    "char": {
      "type": "PATTERN",
      "value": "'[^']'"
    },
    "bool": {
      "type": "CHOICE",
      "members": [
        {
          "type": "STRING",
          "value": "true"
        },
        {
          "type": "STRING",
          "value": "false"
        }
      ]
    },
    "identifier": {
      "type": "PATTERN",
      "value": "[_a-zA-Z][_a-zA-Z0-9]*"
    },
    "_semicolon": {
      "type": "STRING",
      "value": ";"
    }
  },
  "extras": [
    {
      "type": "PATTERN",
      "value": "\\s"
    }
  ],
  "conflicts": [],
  "precedences": [],
  "externals": [],
  "inline": [],
  "supertypes": []
}
